BldCluster/Bld2ReprBld.csv
BldCluster/BldCluster.py
BldCluster/BldMeta.py
BldCluster/Example 1 Classify buildings.py
BldCluster/Representative Buildings.csv
BldCluster/Tool.py
BldCluster/__init__.py
BldCluster/Resources/SanFrancisco_buildings_full.csv
bldcluster-0.1.1.dist-info/METADATA
bldcluster-0.1.1.dist-info/WHEEL
bldcluster-0.1.1.dist-info/licenses/LICENSE
bldcluster-0.1.1.dist-info/RECORD
