Metadata-Version: 2.4
Name: BldCluster
Version: 0.1.1
Summary: 建筑分类工具，根据建筑参数对建筑进行聚类分析
Project-URL: Homepage, https://github.com/youtian95/BldCluster
Project-URL: Bug Tracker, https://github.com/youtian95/BldCluster/issues
Author-email: Tian You <youtian@njtech.edu.cn>
License:                     GNU GENERAL PUBLIC LICENSE
License-File: LICENSE
Requires-Python: >=3.11
Requires-Dist: numpy
Requires-Dist: pandas
Requires-Dist: tqdm
